{
  "slug": "experian",
  "name": "Experian Information Solutions Inc.",
  "display_name": "Experian",
  "data_source": "sample",
  "snapshot_date": "2026-06-29",
  "window": {
    "min": "2025-01-01",
    "max": "2026-06-29"
  },
  "total_complaints": 1600,
  "monthly": [
    {
      "month": "2025-01",
      "count": 32
    },
    {
      "month": "2025-02",
      "count": 44
    },
    {
      "month": "2025-03",
      "count": 58
    },
    {
      "month": "2025-04",
      "count": 62
    },
    {
      "month": "2025-05",
      "count": 72
    },
    {
      "month": "2025-06",
      "count": 88
    },
    {
      "month": "2025-07",
      "count": 101
    },
    {
      "month": "2025-08",
      "count": 105
    },
    {
      "month": "2025-09",
      "count": 93
    },
    {
      "month": "2025-10",
      "count": 111
    },
    {
      "month": "2025-11",
      "count": 107
    },
    {
      "month": "2025-12",
      "count": 102
    },
    {
      "month": "2026-01",
      "count": 94
    },
    {
      "month": "2026-02",
      "count": 88
    },
    {
      "month": "2026-03",
      "count": 114
    },
    {
      "month": "2026-04",
      "count": 121
    },
    {
      "month": "2026-05",
      "count": 97
    },
    {
      "month": "2026-06",
      "count": 111
    }
  ],
  "top_products": [
    {
      "name": "Credit reporting, credit repair services, or other personal consumer reports",
      "count": 1466
    },
    {
      "name": "Debt collection",
      "count": 88
    },
    {
      "name": "Credit card or prepaid card",
      "count": 46
    }
  ],
  "top_issues": [
    {
      "name": "Incorrect information on your report",
      "count": 708
    },
    {
      "name": "Problem with a company's investigation into an existing problem",
      "count": 513
    },
    {
      "name": "Improper use of your report",
      "count": 223
    },
    {
      "name": "Unable to get your credit report or credit score",
      "count": 95
    },
    {
      "name": "Problem with fraud alerts or security freezes",
      "count": 61
    }
  ],
  "top_states": [
    {
      "name": "CA",
      "count": 256
    },
    {
      "name": "TX",
      "count": 248
    },
    {
      "name": "FL",
      "count": 217
    },
    {
      "name": "NY",
      "count": 150
    },
    {
      "name": "GA",
      "count": 140
    },
    {
      "name": "NC",
      "count": 100
    },
    {
      "name": "IL",
      "count": 87
    },
    {
      "name": "PA",
      "count": 79
    },
    {
      "name": "OH",
      "count": 77
    },
    {
      "name": "VA",
      "count": 65
    }
  ],
  "timely_response_rate": 0.985,
  "company_responses": [
    {
      "name": "Closed with explanation",
      "count": 1388
    },
    {
      "name": "Closed with non-monetary relief",
      "count": 162
    },
    {
      "name": "In progress",
      "count": 30
    },
    {
      "name": "Closed with monetary relief",
      "count": 20
    }
  ],
  "narrative_count": 604,
  "sample_narratives": [
    {
      "date": "2026-06-28",
      "product": "Credit card or prepaid card",
      "issue": "Problem with a company's investigation into an existing problem",
      "state": "NJ",
      "text": "There is an account on my credit report that is not mine. I believe this is the result of identity theft and I have disputed it twice with no correction."
    },
    {
      "date": "2026-06-28",
      "product": "Credit reporting, credit repair services, or other personal consumer reports",
      "issue": "Improper use of your report",
      "state": "TX",
      "text": "A fraudulent account was opened in my name. Despite a police report and a fraud alert, the item has not been removed from my report."
    },
    {
      "date": "2026-06-27",
      "product": "Credit reporting, credit repair services, or other personal consumer reports",
      "issue": "Incorrect information on your report",
      "state": "TX",
      "text": "My report shows a late payment that I never had. This error is hurting my score and I was denied a loan because of it."
    },
    {
      "date": "2026-06-27",
      "product": "Credit reporting, credit repair services, or other personal consumer reports",
      "issue": "Problem with a company's investigation into an existing problem",
      "state": "FL",
      "text": "My report shows a late payment that I never had. This error is hurting my score and I was denied a loan because of it."
    },
    {
      "date": "2026-06-27",
      "product": "Credit reporting, credit repair services, or other personal consumer reports",
      "issue": "Incorrect information on your report",
      "state": "TX",
      "text": "My report shows a late payment that I never had. This error is hurting my score and I was denied a loan because of it."
    }
  ],
  "signal": {
    "score": 58,
    "band": "Elevated",
    "components": [
      {
        "key": "timeliness_gap",
        "label": "Untimely responses",
        "weight": 0.15,
        "value": 1.5,
        "evidence": "1.5% of cases not answered on time"
      },
      {
        "key": "relief_gap",
        "label": "Closed without relief",
        "weight": 0.3,
        "value": 88.4,
        "evidence": "88.4% of closed cases ended without monetary or non-monetary relief"
      },
      {
        "key": "issue_concentration",
        "label": "Issue concentration",
        "weight": 0.2,
        "value": 44.3,
        "evidence": "44.3% of complaints share one top issue"
      },
      {
        "key": "trend",
        "label": "Recent trend",
        "weight": 0.2,
        "value": 55.6,
        "evidence": "last 3 months avg 109.7/mo vs prior 98.7/mo"
      },
      {
        "key": "narrative_harm",
        "label": "Harm language in narratives",
        "weight": 0.15,
        "value": 75.2,
        "evidence": "75.2% of 604 narratives mention concrete harm"
      }
    ]
  },
  "summary": "Between 2025-01-01 and 2026-06-29, the CFPB published 1,600 complaints about Experian. Volume is steady (last 3 months averaged 110 per month versus 99 before). The most common issue is \"Incorrect information on your report\" (44% of complaints), concentrated in credit reporting, credit repair services, or other personal consumer reports. The company responded on time to 99% of cases; 88.4% of closed cases ended without relief. Overall risk signal: Elevated (58/100). This is an exploratory signal from public complaint data, not a regulatory, legal, or investment conclusion."
}
