{
  "_note": "Approximate centroids for offline geocoding. States = all 50 + DC. Cities = major US municipalities used by the bundled demo data. Extend `cities` / `counties` to cover more of the Atlas CSV. Format: [latitude, longitude].",
  "_source": "Approximate geographic centers (public domain). For production, replace with the US Census Gazetteer place/county files.",
  "states": {
    "AL": [32.806, -86.791], "AK": [61.370, -152.404], "AZ": [33.729, -111.431],
    "AR": [34.969, -92.373], "CA": [36.116, -119.681], "CO": [39.059, -105.311],
    "CT": [41.597, -72.755], "DE": [39.318, -75.507], "DC": [38.897, -77.026],
    "FL": [27.766, -81.686], "GA": [33.040, -83.643], "HI": [21.094, -157.498],
    "ID": [44.240, -114.478], "IL": [40.349, -88.986], "IN": [39.849, -86.258],
    "IA": [42.011, -93.210], "KS": [38.526, -96.726], "KY": [37.668, -84.670],
    "LA": [31.169, -91.867], "ME": [44.693, -69.381], "MD": [39.064, -76.802],
    "MA": [42.230, -71.530], "MI": [43.326, -84.536], "MN": [45.694, -93.900],
    "MS": [32.741, -89.678], "MO": [38.456, -92.288], "MT": [46.921, -110.454],
    "NE": [41.125, -98.268], "NV": [38.313, -117.055], "NH": [43.452, -71.563],
    "NJ": [40.298, -74.521], "NM": [34.840, -106.248], "NY": [42.165, -74.948],
    "NC": [35.630, -79.806], "ND": [47.528, -99.784], "OH": [40.388, -82.764],
    "OK": [35.565, -96.928], "OR": [44.572, -122.071], "PA": [40.590, -77.209],
    "RI": [41.680, -71.511], "SC": [33.856, -80.945], "SD": [44.299, -99.438],
    "TN": [35.747, -86.692], "TX": [31.054, -97.563], "UT": [40.150, -111.862],
    "VT": [44.045, -72.710], "VA": [37.769, -78.170], "WA": [47.400, -121.490],
    "WV": [38.491, -80.954], "WI": [44.268, -89.616], "WY": [42.756, -107.302]
  },
  "cities": {
    "oakland|CA": [37.804, -122.271], "san francisco|CA": [37.775, -122.419],
    "los angeles|CA": [34.052, -118.244], "san diego|CA": [32.716, -117.161],
    "sacramento|CA": [38.582, -121.494], "fresno|CA": [36.747, -119.772],
    "san jose|CA": [37.339, -121.895], "long beach|CA": [33.770, -118.194],
    "new york|NY": [40.713, -74.006], "buffalo|NY": [42.886, -78.878],
    "rochester|NY": [43.161, -77.611], "albany|NY": [42.652, -73.757],
    "chicago|IL": [41.878, -87.630], "aurora|IL": [41.761, -88.320],
    "houston|TX": [29.760, -95.370], "dallas|TX": [32.777, -96.797],
    "austin|TX": [30.267, -97.743], "san antonio|TX": [29.424, -98.494],
    "fort worth|TX": [32.756, -97.331], "el paso|TX": [31.759, -106.487],
    "phoenix|AZ": [33.448, -112.074], "tucson|AZ": [32.222, -110.974],
    "mesa|AZ": [33.415, -111.831], "seattle|WA": [47.606, -122.332],
    "spokane|WA": [47.659, -117.426], "tacoma|WA": [47.253, -122.444],
    "portland|OR": [45.515, -122.679], "eugene|OR": [44.052, -123.087],
    "denver|CO": [39.739, -104.990], "colorado springs|CO": [38.834, -104.821],
    "boston|MA": [42.360, -71.058], "worcester|MA": [42.263, -71.802],
    "detroit|MI": [42.331, -83.046], "grand rapids|MI": [42.963, -85.668],
    "atlanta|GA": [33.749, -84.388], "savannah|GA": [32.081, -81.091],
    "miami|FL": [25.762, -80.192], "orlando|FL": [28.538, -81.379],
    "tampa|FL": [27.951, -82.457], "jacksonville|FL": [30.332, -81.656],
    "minneapolis|MN": [44.978, -93.265], "saint paul|MN": [44.954, -93.090],
    "philadelphia|PA": [39.953, -75.165], "pittsburgh|PA": [40.441, -79.996],
    "baltimore|MD": [39.290, -76.612], "washington|DC": [38.907, -77.037],
    "nashville|TN": [36.163, -86.781], "memphis|TN": [35.150, -90.049],
    "new orleans|LA": [29.951, -90.072], "charlotte|NC": [35.227, -80.843],
    "raleigh|NC": [35.780, -78.639], "columbus|OH": [39.961, -82.999],
    "cleveland|OH": [41.500, -81.694], "cincinnati|OH": [39.103, -84.512],
    "indianapolis|IN": [39.768, -86.158], "milwaukee|WI": [43.039, -87.906],
    "kansas city|MO": [39.100, -94.579], "st louis|MO": [38.627, -90.198],
    "saint louis|MO": [38.627, -90.198], "las vegas|NV": [36.170, -115.140],
    "reno|NV": [39.530, -119.814], "salt lake city|UT": [40.761, -111.891],
    "albuquerque|NM": [35.085, -106.651], "oklahoma city|OK": [35.468, -97.516],
    "tulsa|OK": [36.154, -95.993], "louisville|KY": [38.253, -85.758],
    "birmingham|AL": [33.519, -86.810], "newark|NJ": [40.736, -74.172],
    "jersey city|NJ": [40.728, -74.078], "providence|RI": [41.824, -71.413],
    "hartford|CT": [41.764, -72.685], "richmond|VA": [37.541, -77.436],
    "virginia beach|VA": [36.853, -75.978], "honolulu|HI": [21.307, -157.858],
    "anchorage|AK": [61.218, -149.900], "boise|ID": [43.615, -116.202],
    "des moines|IA": [41.587, -93.625], "wichita|KS": [37.687, -97.336]
  },
  "counties": {
    "alameda|CA": [37.601, -121.720], "los angeles|CA": [34.196, -118.262],
    "cook|IL": [41.841, -87.816], "harris|TX": [29.857, -95.393],
    "maricopa|AZ": [33.349, -112.491], "king|WA": [47.491, -121.834],
    "miami-dade|FL": [25.611, -80.498], "fulton|GA": [33.790, -84.467]
  }
}
